blueice/__init__.py
blueice/data_reading.py
blueice/exceptions.py
blueice/inference.py
blueice/likelihood.py
blueice/model.py
blueice/parallel.py
blueice/pdf_morphers.py
blueice/source.py
blueice/test_helpers.py
blueice/utils.py
blueice-1.2.1.dist-info/LICENSE
blueice-1.2.1.dist-info/METADATA
blueice-1.2.1.dist-info/WHEEL
blueice-1.2.1.dist-info/top_level.txt
blueice-1.2.1.dist-info/RECORD
