Metadata-Version: 2.1
Name: blueice
Version: 1.2.1
Summary: Build Likelihoods Using Efficient Interpolations from monte-Carlo generated Events
Home-page: https://github.com/JelleAalbers/blueice
Author: Jelle Aalbers
Author-email: j.aalbers@uva.nl
License: MIT
Keywords: blueice
Platform: UNKNOWN
Classifier: Intended Audience :: Developers
Classifier: License :: OSI Approved :: MIT License
Classifier: Natural Language :: English
Classifier: Programming Language :: Python :: 3.8
Classifier: Programming Language :: Python :: 3.9
Classifier: Intended Audience :: Science/Research
Classifier: Programming Language :: Python :: Implementation :: CPython
Classifier: Topic :: Scientific/Engineering :: Physics
License-File: LICENSE
Requires-Dist: wheel>=0.23.0
Requires-Dist: numpy>=1.9.0
Requires-Dist: pandas
Requires-Dist: dill
Requires-Dist: scipy>=0.15
Requires-Dist: tqdm
Requires-Dist: multihist>=0.4.3
Requires-Dist: pytest>=3.0.0
Requires-Dist: atomicwrites
